shadowserver_api/__init__.py
shadowserver_api/api.py
shadowserver_api/async_api.py
shadowserver_api/exceptions.py
shadowserver_api/py.typed
shadowserver_api-0.4.0.dist-info/LICENSE
shadowserver_api-0.4.0.dist-info/METADATA
shadowserver_api-0.4.0.dist-info/WHEEL
shadowserver_api-0.4.0.dist-info/top_level.txt
shadowserver_api-0.4.0.dist-info/RECORD
