Metadata-Version: 2.1
Name: shadowserver_api
Version: 0.4.0
Summary: Shadowserver API implementation library
Author-email: Georges Toth <georges.toth@govcert.etat.lu>
License: AGPLv3+
Project-URL: Homepage, https://github.com/GOVCERT-LU/shadowserver_api
Keywords: shadowserver
Classifier: Development Status :: 4 - Beta
Classifier: License :: OSI Approved :: GNU Affero General Public License v3 or later (AGPLv3+)
Classifier: Intended Audience :: Developers
Classifier: Operating System :: OS Independent
Classifier: Programming Language :: Python :: 3 :: Only
Classifier: Programming Language :: Python :: 3.8
Classifier: Programming Language :: Python :: 3.9
Classifier: Programming Language :: Python :: 3.10
Classifier: Programming Language :: Python :: 3.11
Classifier: Programming Language :: Python :: 3.12
Requires-Python: >=3.8
License-File: LICENSE
Requires-Dist: pyyaml
Requires-Dist: httpx
Provides-Extra: dev
Requires-Dist: mypy ; extra == 'dev'
Requires-Dist: ruff ; extra == 'dev'
Requires-Dist: unasyncd ; extra == 'dev'
Provides-Extra: docs
Requires-Dist: mkdocs-material ; extra == 'docs'
Requires-Dist: mkdocstrings[python] >=0.18 ; extra == 'docs'
Provides-Extra: test
Requires-Dist: pytest ; extra == 'test'
Requires-Dist: coverage ; extra == 'test'
